wvu/__init__.py
wvu/util.py
wvu-0.3.9.dist-info/LICENSE
wvu-0.3.9.dist-info/METADATA
wvu-0.3.9.dist-info/WHEEL
wvu-0.3.9.dist-info/top_level.txt
wvu-0.3.9.dist-info/RECORD
