Metadata-Version: 2.1
Name: wvu
Version: 0.3.9
Summary: Simple utilities for teaching Pandas and scikit learn.
Home-page: https://github.com/WinVector/wvu
Author: John Mount
Author-email: jmount@win-vector.com
License: License :: OSI Approved :: BSD 3-clause License
Platform: any
Classifier: Intended Audience :: Science/Research
Classifier: Programming Language :: Python
Classifier: Programming Language :: Python :: 3
Classifier: Programming Language :: Python :: 3.5
Classifier: Programming Language :: Python :: 3.6
Classifier: Programming Language :: Python :: 3.7
Classifier: Programming Language :: Python :: 3.8
Classifier: Programming Language :: Python :: 3.9
Classifier: Programming Language :: Python :: 3.10
Classifier: Programming Language :: Python :: 3.11
Classifier: License :: OSI Approved :: BSD License
License-File: LICENSE
Requires-Dist: numpy
Requires-Dist: pandas
Requires-Dist: scikit-learn
Requires-Dist: seaborn
Requires-Dist: matplotlib
Requires-Dist: vtreat (>=1.2.4)
Requires-Dist: wvpy (>=0.3.5)
Requires-Dist: data-algebra (>=1.4.1)
